pdate_cli/__init__.py
pdate_cli/cli.py
pdate_cli-0.1.0.dist-info/METADATA
pdate_cli-0.1.0.dist-info/WHEEL
pdate_cli-0.1.0.dist-info/entry_points.txt
pdate_cli-0.1.0.dist-info/RECORD
