Metadata-Version: 2.1
Name: pdate_cli
Version: 0.1.0
Summary: PDate converts dates to human-readable formats.
Author: Hunter Gatewood
Author-email: hgatewood@gmail.com
Requires-Python: >=3.12,<4.0
Classifier: Programming Language :: Python :: 3
Classifier: Programming Language :: Python :: 3.12
Requires-Dist: click (>=8.0.0,<9.0.0)
Requires-Dist: dateparser (>=1.2.2,<2.0.0)
Requires-Dist: humanize (>=4.12.3,<5.0.0)
Requires-Dist: python-dateutil (>=2.8.2,<3.0.0)
